rockstore/__init__.py
rockstore/context.py
rockstore/py.typed
rockstore/store.py
rockstore-0.1.2.dist-info/licenses/LICENSE
rockstore-0.1.2.dist-info/METADATA
rockstore-0.1.2.dist-info/WHEEL
rockstore-0.1.2.dist-info/top_level.txt
rockstore-0.1.2.dist-info/RECORD
