Metadata-Version: 2.4
Name: rockstore
Version: 0.1.2
Summary: A lightweight Python wrapper for RocksDB using CFFI
Author-email: Prasad Kumkar <prasad@chainscore.finance>, Chainscore Labs <hello@chainscore.finance>
License: MIT
Project-URL: Homepage, https://github.com/chainscore/rockstore
Project-URL: Documentation, https://github.com/chainscore/rockstore#readme
Project-URL: Repository, https://github.com/chainscore/rockstore
Project-URL: Bug Tracker, https://github.com/chainscore/rockstore/issues
Keywords: rocksdb,database,key-value,cffi,embedded
Classifier: Development Status :: 4 - Beta
Classifier: Intended Audience :: Developers
Classifier: License :: OSI Approved :: MIT License
Classifier: Programming Language :: Python :: 3
Classifier: Programming Language :: Python :: 3.8
Classifier: Programming Language :: Python :: 3.9
Classifier: Programming Language :: Python :: 3.10
Classifier: Programming Language :: Python :: 3.11
Classifier: Programming Language :: Python :: 3.12
Classifier: Topic :: Database
Classifier: Topic :: Software Development :: Libraries :: Python Modules
Requires-Python: >=3.8
License-File: LICENSE
Requires-Dist: cffi>=1.15.0
Provides-Extra: dev
Requires-Dist: pytest>=7.0.0; extra == "dev"
Requires-Dist: pytest-benchmark>=4.0.0; extra == "dev"
Dynamic: license-file
